dlens/__init__.py
dlens/__version__.py
dlens/cli.py
dlens/config/__init__.py
dlens/config/config_manager.py
dlens/core/__init__.py
dlens/core/directory_mapper.py
dlens/core/platform_handler.py
dlens/core/progress_tracker.py
dlens/core/search_handler.py
dlens/resources/__init__.py
dlens/resources/icons.json
dlens/resources/resources_manager.py
dlens/resources/themes.json
dlens/resources/templates/directory_map.html
dlens/resources/templates/search_template.html
dlens/ui/__init__.py
dlens/ui/file_icons.py
dlens/ui/theme_manager.py
dlens/utils/__init__.py
dlens/utils/exporters.py
dlens/utils/size_formatter.py
dlens/utils/stats_collector.py
dlens-1.0.0.dist-info/licenses/LICENSE.md
dlens-1.0.0.dist-info/METADATA
dlens-1.0.0.dist-info/WHEEL
dlens-1.0.0.dist-info/entry_points.txt
dlens-1.0.0.dist-info/top_level.txt
dlens-1.0.0.dist-info/RECORD
