Metadata-Version: 2.4
Name: dlens
Version: 1.0.0
Summary: Enhanced directory mapping and visualization tool
Home-page: https://github.com/Muhammad-NSQ/Dlens
Author: Muhammad-NSQ
Author-email: Your Name <your.email@example.com>
License: MIT
Project-URL: Homepage, https://github.com/Muhammad-NSQ/Dlens
Project-URL: Bug Reports, https://github.com/Muhammad-NSQ/Dlens/issues
Project-URL: Source, https://github.com/Muhammad-NSQ/Dlens
Project-URL: Documentation, https://github.com/Muhammad-NSQ/Dlens#readme
Keywords: directory,mapping,filesystem,visualization,cli,tree
Classifier: Development Status :: 4 - Beta
Classifier: Intended Audience :: Developers
Classifier: Intended Audience :: System Administrators
Classifier: Topic :: System :: Filesystems
Classifier: Topic :: Utilities
Classifier: License :: OSI Approved :: MIT License
Classifier: Programming Language :: Python :: 3
Classifier: Programming Language :: Python :: 3.8
Classifier: Programming Language :: Python :: 3.9
Classifier: Programming Language :: Python :: 3.10
Classifier: Programming Language :: Python :: 3.11
Classifier: Programming Language :: Python :: 3.12
Classifier: Operating System :: OS Independent
Classifier: Environment :: Console
Requires-Python: >=3.8
License-File: LICENSE.md
Requires-Dist: click>=8.0.0
Requires-Dist: rich>=12.0.0
Requires-Dist: jinja2>=3.0.0
Provides-Extra: dev
Requires-Dist: pytest>=6.0; extra == "dev"
Requires-Dist: pytest-cov; extra == "dev"
Requires-Dist: black; extra == "dev"
Requires-Dist: flake8; extra == "dev"
Requires-Dist: mypy; extra == "dev"
Provides-Extra: test
Requires-Dist: pytest>=6.0; extra == "test"
Requires-Dist: pytest-cov; extra == "test"
Dynamic: author
Dynamic: home-page
Dynamic: license-file
Dynamic: requires-python
